cspresso/__init__.py
cspresso/__main__.py
cspresso/crawl.py
cspresso/ensure_playwright.py
cspresso-0.1.3.dist-info/LICENSE
cspresso-0.1.3.dist-info/METADATA
cspresso-0.1.3.dist-info/WHEEL
cspresso-0.1.3.dist-info/entry_points.txt
cspresso-0.1.3.dist-info/RECORD
