Metadata-Version: 2.1
Name: cspresso
Version: 0.1.3
Summary: Crawl a website with a headless browser and generate a draft Content-Security-Policy (CSP).
Home-page: https://cspresso.cafe
License: GPL-3.0-or-later
Author: Miguel Jacq
Author-email: mig@mig5.net
Requires-Python: >=3.10,<4.0
Classifier: License :: OSI Approved :: GNU General Public License v3 or later (GPLv3+)
Classifier: Programming Language :: Python :: 3
Classifier: Programming Language :: Python :: 3.10
Classifier: Programming Language :: Python :: 3.11
Classifier: Programming Language :: Python :: 3.12
Requires-Dist: playwright (>=1.50.0,<2.0.0)
Project-URL: Repository, https://git.mig5.net/mig5/cspresso
